Code/rtl/fsm_1_always.sv
/*
                      rst                 
                       │  ┌───┐           
                       │  │   │           
                       ▼  ▼   │start=0    
                  ┌─────────┐ │           
                  │  IDLE   ├─┘           
                  │         │             
         ┌───────▶│  rd=0   ├──────────┐  
         │        │  ds=0   │ start=1  │  
         │        └─────────┘          │  
         │                             │  
         │                             ▼  
    ┌────┴────┐                ┌─────────┐
    │  DONE   │                │  READ   │
    │         │                │         │
    │  rd=0   │                │  rd=1   │
    │  ds=1   │                │  ds=0   │
    └─────────┘                └─┬───────┘
         ▲                       │     ▲  
         │        ┌─────────┐    │     │  
         │        │   DLY   │◀───┘     │  
         │        │         │          │  
         │        │  rd=1   │          │  
         └────────┤  ds=0   ├──────────┘  
            ws=0  └─────────┘  ws=1       


                               seq       
                        ┌───────┐        
                   next │Outputs│        
                outputs │  FF   │outputs 
    inputs────┐     ┌──▶│       ├────▶   
              │     │   └───────┘        
              ▼ comb│                    
          ┌───────┐ │                    
          │       ├─┘          seq       
          │ Next  │     ┌───────┐        
          │ state │     │  FSM  │        
     state│ logic │next │ state │state   
       ┌─▶│       ├────▶│  FF   ├─┐      
       │  └───────┘     └───────┘ │      
       └──────────────────────────┘      
*/

module fsm_1_always (
    output reg rd,
    output reg ds,

    input clk,
    input rst,

    input start,
    input ws
);

  localparam IDLE = "IDLE";
  localparam READ = "READ";
  localparam DLY = "DLY";
  localparam DONE = "DONE";

  localparam UNKW = 'x;

  reg [4*8-1:0] cstate;

  always_ff @(posedge clk, posedge rst) begin
    if (rst) begin
      cstate <= IDLE;
      rd     <= 0;
      ds     <= 0;
    end else begin
      cstate <= UNKW;  // Need @LB
      rd <= 0;
      ds <= 0;
      case (cstate)
        IDLE:
        if (start) begin
          cstate <= READ;
          rd     <= 1;
        end else cstate <= IDLE;  // @LB
        READ: begin
          cstate <= DLY;
          rd     <= 1;
        end
        DLY:
        if (ws) begin
          cstate <= READ;
          rd     <= 1;
        end else begin
          cstate <= DONE;
          ds     <= 1;
        end
        DONE: cstate <= IDLE;
        default: begin
          cstate <= UNKW;
          rd     <= UNKW;
          ds     <= UNKW;
        end
      endcase
    end
  end

endmodule

Code/tb/test_fsm.sv
/*
                      rst                 
                       │  ┌───┐           
                       │  │   │           
                       ▼  ▼   │start=0    
                  ┌─────────┐ │           
                  │  IDLE   ├─┘           
                  │         │             
         ┌───────▶│  rd=0   ├──────────┐  
         │        │  ds=0   │ start=1  │  
         │        └─────────┘          │  
         │                             │  
         │                             ▼  
    ┌────┴────┐                ┌─────────┐
    │  DONE   │                │  READ   │
    │         │                │         │
    │  rd=0   │                │  rd=1   │
    │  ds=1   │                │  ds=0   │
    └─────────┘                └─┬───────┘
         ▲                       │     ▲  
         │        ┌─────────┐    │     │  
         │        │   DLY   │◀───┘     │  
         │        │         │          │  
         │        │  rd=1   │          │  
         └────────┤  ds=0   ├──────────┘  
            ws=0  └─────────┘  ws=1       
*/

module test_fsm;

  // Parameters
  localparam CLK_PERIOD = 10;

  // Ports
  wire rd;
  wire ds;
  reg  clk = 0;
  reg  rst = 0;
  reg  start = 0;
  reg  ws = 0;

  fsm_1_always fsm_always_dut (
      .rd(rd),
      .ds(ds),

      .clk(clk),
      .rst(rst),

      .start(start),
      .ws   (ws)
  );

  initial begin
    begin
      $dumpfile("test_fsm.vcd");
      $dumpvars;
      reset(3);
      test();
      nop_clk(3);
      $finish;
    end
  end

  task automatic test;
    begin
      nop_clk(3);
      start = 1;
      @(negedge clk);
      start = 0;

      ws = 1;
      nop_clk(5);
      ws = 0;
    end
  endtask  //automatic

  task automatic reset;
    input integer n;
    rst = 1;
    repeat (n) @(negedge clk);
    rst = 0;
  endtask  //automatic

  task automatic nop_clk;
    input integer n;
    repeat (n) @(negedge clk);
  endtask  //automatic

  always #(CLK_PERIOD / 2) clk = !clk;

endmodule

Code/rtl/fsm_4_always.sv
/*
                      rst                 
                       │  ┌───┐           
                       │  │   │           
                       ▼  ▼   │start=0    
                  ┌─────────┐ │           
                  │  IDLE   ├─┘           
                  │         │             
         ┌───────▶│  rd=0   ├──────────┐  
         │        │  ds=0   │ start=1  │  
         │        └─────────┘          │  
         │                             │  
         │                             ▼  
    ┌────┴────┐                ┌─────────┐
    │  DONE   │                │  READ   │
    │         │                │         │
    │  rd=0   │                │  rd=1   │
    │  ds=1   │                │  ds=0   │
    └─────────┘                └─┬───────┘
         ▲                       │     ▲  
         │        ┌─────────┐    │     │  
         │        │   DLY   │◀───┘     │  
         │        │         │          │  
         │        │  rd=1   │          │  
         └────────┤  ds=0   ├──────────┘  
            ws=0  └─────────┘  ws=1       


    inputs                                       
       │              comb             seq       
       │  inputs┌───────┐       ┌───────┐        
       ●───────▶│ Next  │next   │Outputs│        
       │  state │outputs│outputs│  FF   │outputs 
       │     ┌─▶│ logic ├──────▶│       ├────▶   
       │     │  └───────┘       └───────┘        
       │     │        comb            seq        
       │ inputs ┌───────┐       ┌───────┐        
       └─────┼─▶│ Next  │       │  FSM  │        
          state │ state │ next  │ state │state   
             ●─▶│ logic ├──────▶│  FF   ├─┐      
             │  └───────┘       └───────┘ │      
             └────────────────────────────┘      
*/

module fsm_4_always (
    output reg rd,
    output reg ds,

    input clk,
    input rst,

    input start,
    input ws
);

  localparam IDLE = "IDLE";
  localparam READ = "READ";
  localparam DLY =  "DLY";
  localparam DONE = "DONE";

  localparam UNKW = 'x;

  reg [4*8-1:0] cstate;
  reg [4*8-1:0] nstate;

  always_ff @(posedge clk, posedge rst)
    if (rst) cstate <= IDLE;
    else cstate <= nstate;

  always_comb begin
    nstate = UNKW;  // @LB nstate = cstate;
    case (cstate)
      IDLE:    nstate = start ? READ : IDLE;
      READ:    nstate = DLY;
      DLY:     nstate = ws ? READ : DONE;
      DONE:    nstate = IDLE;
      default: nstate = UNKW;
    endcase
  end

  reg nrd;  // next rd
  reg nds;  // next ds

  always_comb begin
    nrd = 0;
    nds = 0;
    case (cstate)
      IDLE:    if(start) nrd = 1;
      READ:    nrd = 1;
      DLY: begin
        if (ws) nrd = 1;
        else nds = 1;
      end
      DONE: ;
      default: {nrd, nds} = UNKW;
    endcase
  end

  always_ff @(posedge clk, posedge rst) begin
    if (rst) begin
      rd <= 0;
      ds <= 0;
    end else begin
      rd <= nrd;
      ds <= nds;
    end
  end

endmodule

Code/rtl/fsm_3_always.sv
/*
                      rst                 
                       │  ┌───┐           
                       │  │   │           
                       ▼  ▼   │start=0    
                  ┌─────────┐ │           
                  │  IDLE   ├─┘           
                  │         │             
         ┌───────▶│  rd=0   ├──────────┐  
         │        │  ds=0   │ start=1  │  
         │        └─────────┘          │  
         │                             │  
         │                             ▼  
    ┌────┴────┐                ┌─────────┐
    │  DONE   │                │  READ   │
    │         │                │         │
    │  rd=0   │                │  rd=1   │
    │  ds=1   │                │  ds=0   │
    └─────────┘                └─┬───────┘
         ▲                       │     ▲  
         │        ┌─────────┐    │     │  
         │        │   DLY   │◀───┘     │  
         │        │         │          │  
         │        │  rd=1   │          │  
         └────────┤  ds=0   ├──────────┘  
            ws=0  └─────────┘  ws=1       


                              comb             seq       
                        ┌───────┐       ┌───────┐        
                        │ Next  │next   │Outputs│        
                   next │outputs│outputs│  FF   │outputs 
    inputs────┐     ┌──▶│ logic ├──────▶│       ├────▶   
              │     │   └───────┘       └───────┘        
              ▼ comb│          seq                       
          ┌───────┐ │   ┌───────┐                        
          │ Next  │ │   │  FSM  │                        
     state│ state │ │   │ state │state                   
       ┌─▶│ logic ├─●──▶│  FF   ├─┐                      
       │  └───────┘next └───────┘ │                      
       └──────────────────────────┘                      
*/

module fsm_3_always (
    output reg rd,
    output reg ds,

    input clk,
    input rst,

    input start,
    input ws
);

  localparam IDLE = "IDLE";
  localparam READ = "READ";
  localparam DLY = "DLY";
  localparam DONE = "DONE";

  localparam UNKW = 'x;

  reg [4*8-1:0] cstate;
  reg [4*8-1:0] nstate;

  always_ff @(posedge clk, posedge rst)
    if (rst) cstate <= IDLE;
    else cstate <= nstate;

  always_comb begin
    nstate = UNKW;  // @LB nstate = cstate;
    case (cstate)
      IDLE:    nstate = start ? READ : IDLE;
      READ:    nstate = DLY;
      DLY:     nstate = ws ? READ : DONE;
      DONE:    nstate = IDLE;
      default: nstate = UNKW;
    endcase
  end

  always_ff @(posedge clk, posedge rst) begin
    if (rst) begin
      rd <= 0;
      ds <= 0;
    end else begin
      rd <= 0;
      ds <= 0;
      case (nstate)
        IDLE:    ;
        READ:    rd <= 1;
        DLY:     rd <= 1;
        DONE:    ds <= 1;
        default: {rd, ds} <= UNKW;
      endcase
    end
  end

endmodule

Code/rtl/fsm_2_always.sv
/*
                      rst                 
                       │  ┌───┐           
                       │  │   │           
                       ▼  ▼   │start=0    
                  ┌─────────┐ │           
                  │  IDLE   ├─┘           
                  │         │             
         ┌───────▶│  rd=0   ├──────────┐  
         │        │  ds=0   │ start=1  │  
         │        └─────────┘          │  
         │                             │  
         │                             ▼  
    ┌────┴────┐                ┌─────────┐
    │  DONE   │                │  READ   │
    │         │                │         │
    │  rd=0   │                │  rd=1   │
    │  ds=1   │                │  ds=0   │
    └─────────┘                └─┬───────┘
         ▲                       │     ▲  
         │        ┌─────────┐    │     │  
         │        │   DLY   │◀───┘     │  
         │        │         │          │  
         │        │  rd=1   │          │  
         └────────┤  ds=0   ├──────────┘  
            ws=0  └─────────┘  ws=1       



    inputs────┐                                        
              │                                        
              ▼ comb           seq          comb       
          ┌───────┐     ┌───────┐     ┌───────┐        
          │ Next  │     │  FSM  │     │Outputs│        
     state│ state │next │ state │state│ logic │outputs 
       ┌─▶│ logic ├────▶│       ├─●──▶│       ├────▶   
       │  └───────┘     └───────┘ │   └───────┘        
       └──────────────────────────┘                    
*/

module fsm_2_always (
    output reg rd,
    output reg ds,

    input clk,
    input rst,

    input start,
    input ws
);

  localparam IDLE = "IDLE";
  localparam READ = "READ";
  localparam DLY = "DLY";
  localparam DONE = "DONE";

  localparam UNKW = 'x;

  reg [4*8-1:0] cstate;
  reg [4*8-1:0] nstate;

  always_ff @(posedge clk, posedge rst)
    if (rst) cstate <= IDLE;
    else cstate <= nstate;

  // /*
  always_comb begin
    nstate = UNKW;  // Need @LB
    rd = 0;
    ds = 0;
    case (cstate)
      IDLE: nstate = start ? READ : IDLE;
      READ: begin
        nstate = DLY;
        rd     = 1;
      end
      DLY: begin
        nstate = ws ? READ : DONE;
        rd     = 1;
      end
      DONE: begin
        nstate = IDLE;
        ds     = 1;
      end
      default: begin
        nstate = UNKW;
        rd     = UNKW;
        ds     = UNKW;
      end
    endcase
  end
  // */

  /*
  // For added flexibility, outputs can optionally be moved out of the main `always_comb` block
  // and placed in a separate `always_comb` block or defined through continuous assignment statements.
  // This modular approach helps in managing and organizing the next-state and output logic distinctly.

  always_comb begin
    nstate = UNKW;  // @LB nstate = cstate;
    case (cstate)
      IDLE:    nstate = start ? READ : IDLE;
      READ:    nstate = DLY;
      DLY:     nstate = ws ? READ : DONE;
      DONE:    nstate = IDLE;
      default: nstate = UNKW;
    endcase
  end

  always_comb begin
    rd = 0;
    ds = 0;
    case (cstate)
      READ:    rd = 1;
      DLY:     rd = 1;
      DONE:    ds = 1;
      default: {rd, ds} = UNKW;
    endcase
  end
  // */

endmodule

Code/test_fsm.vcd
$date
	Wed Oct 30 18:23:17 2024
$end
$version
	Icarus Verilog
$end
$timescale
	1s
$end
$scope module fsm_2_always $end
$var wire 1 ! clk $end
$var wire 1 " rst $end
$var wire 1 # start $end
$var wire 1 $ ws $end
$var parameter 24 % DLY $end
$var parameter 32 & DONE $end
$var parameter 32 ' IDLE $end
$var parameter 32 ( READ $end
$var parameter 1 ) UNKW $end
$var reg 32 * cstate [31:0] $end
$var reg 1 + ds $end
$var reg 32 , nstate [31:0] $end
$var reg 1 - rd $end
$upscope $end
$scope module fsm_3_always $end
$var wire 1 . clk $end
$var wire 1 / rst $end
$var wire 1 0 start $end
$var wire 1 1 ws $end
$var parameter 24 2 DLY $end
$var parameter 32 3 DONE $end
$var parameter 32 4 IDLE $end
$var parameter 32 5 READ $end
$var parameter 1 6 UNKW $end
$var reg 32 7 cstate [31:0] $end
$var reg 1 8 ds $end
$var reg 32 9 nstate [31:0] $end
$var reg 1 : rd $end
$upscope $end
$scope module fsm_4_always $end
$var wire 1 ; clk $end
$var wire 1 < rst $end
$var wire 1 = start $end
$var wire 1 > ws $end
$var parameter 24 ? DLY $end
$var parameter 32 @ DONE $end
$var parameter 32 A IDLE $end
$var parameter 32 B READ $end
$var parameter 1 C UNKW $end
$var reg 32 D cstate [31:0] $end
$var reg 1 E ds $end
$var reg 1 F nds $end
$var reg 1 G nrd $end
$var reg 32 H nstate [31:0] $end
$var reg 1 I rd $end
$upscope $end
$scope module test_fsm $end
$var wire 1 J rd $end
$var wire 1 K ds $end
$var parameter 32 L CLK_PERIOD $end
$var reg 1 M clk $end
$var reg 1 N rst $end
$var reg 1 O start $end
$var reg 1 P ws $end
$scope module fsm_always_dut $end
$var wire 1 M clk $end
$var wire 1 N rst $end
$var wire 1 O start $end
$var wire 1 P ws $end
$var parameter 24 Q DLY $end
$var parameter 32 R DONE $end
$var parameter 32 S IDLE $end
$var parameter 32 T READ $end
$var parameter 1 U UNKW $end
$var reg 32 V cstate [31:0] $end
$var reg 1 K ds $end
$var reg 1 J rd $end
$upscope $end
$scope task nop_clk $end
$upscope $end
$scope task reset $end
$upscope $end
$scope task test $end
$upscope $end
$upscope $end
$enddefinitions $end
$comment Show the parameter values. $end
$dumpall
xU
b1010010010001010100000101000100 T
b1001001010001000100110001000101 S
b1000100010011110100111001000101 R
b10001000100110001011001 Q
b1010 L
xC
b1010010010001010100000101000100 B
b1001001010001000100110001000101 A
b1000100010011110100111001000101 @
b10001000100110001011001 ?
x6
b1010010010001010100000101000100 5
b1001001010001000100110001000101 4
b1000100010011110100111001000101 3
b10001000100110001011001 2
x)
b1010010010001010100000101000100 (
b1001001010001000100110001000101 '
b1000100010011110100111001000101 &
b10001000100110001011001 %
$end
#0
$dumpvars
b1001001010001000100110001000101 V
0P
0O
1N
0M
0K
0J
xI
b0x H
0G
xF
xE
bx D
z>
z=
z<
z;
x:
b0x 9
x8
bx 7
z1
z0
z/
z.
x-
b0x ,
x+
bx *
z$
z#
z"
z!
$end
#5
1M
#10
0M
#15
1M
#20
0M
#25
1M
#30
0N
0M
#35
b1001001010001000100110001000101 V
1M
#40
0M
#45
b1001001010001000100110001000101 V
1M
#50
0M
#55
b1001001010001000100110001000101 V
1M
#60
1O
0M
#65
1J
b1010010010001010100000101000100 V
1M
#70
1P
0O
0M
#75
1J
b10001000100110001011001 V
1M
#80
0M
#85
1J
b1010010010001010100000101000100 V
1M
#90
0M
#95
1J
b10001000100110001011001 V
1M
#100
0M
#105
1J
b1010010010001010100000101000100 V
1M
#110
0M
#115
1J
b10001000100110001011001 V
1M
#120
0P
0M
#125
1K
0J
b1000100010011110100111001000101 V
1M
#130
0M
#135
0K
b1001001010001000100110001000101 V
1M
#140
0M
#145
b1001001010001000100110001000101 V
1M
